topmovies/__init__.py
topmovies/get_movie_data.py
topmovies/top_movies.py
topmovies-0.1.7.dist-info/METADATA
topmovies-0.1.7.dist-info/WHEEL
topmovies-0.1.7.dist-info/RECORD
