Metadata-Version: 2.1
Name: topmovies
Version: 0.1.7
Summary: 
Author: zhanghuihui111
Author-email: 2019110851@stu.sufe.edu.cn
Requires-Python: >=3.12,<4.0
Classifier: Programming Language :: Python :: 3
Classifier: Programming Language :: Python :: 3.12
Requires-Dist: beautifulsoup4 (>=4.12.3,<5.0.0)
Requires-Dist: pytest (>=8.3.2,<9.0.0)
Requires-Dist: requests (>=2.32.3,<3.0.0)
Requires-Dist: requests-mock (>=1.12.1,<2.0.0)
